LICENSE
README.rst
setup.py
corona_rayo.egg-info/PKG-INFO
corona_rayo.egg-info/SOURCES.txt
corona_rayo.egg-info/dependency_links.txt
corona_rayo.egg-info/requires.txt
corona_rayo.egg-info/top_level.txt
rayo/connector.py
rayo/handler.py
rayo/settings.py