Metadata-Version: 2.1
Name: corona-rayo
Version: 1.0.6
Summary: Django Rayo Integration
Home-page: https://gitlab.com/linets-projects/python-libraries/django-rayo/
Author: Corona Development Team
Author-email: rolguin@corona.cl
License: MIT
Platform: UNKNOWN
Requires-Python: >=3.7
License-File: LICENSE
